com/__init__.py
com/lhw/__init__.py
com/lhw/bubble/__init__.py
com/lhw/bubble/richer.py
GiveMeARichNumber-0.0.2.dist-info/LICENSE
GiveMeARichNumber-0.0.2.dist-info/METADATA
GiveMeARichNumber-0.0.2.dist-info/WHEEL
GiveMeARichNumber-0.0.2.dist-info/entry_points.txt
GiveMeARichNumber-0.0.2.dist-info/top_level.txt
GiveMeARichNumber-0.0.2.dist-info/RECORD
